{
  "done": [
    "goblin",
    "knight",
    "polearm",
    "spellsword",
    "battlemage",
    "archer",
    "woodsWitch",
    "wizard",
    "lich",
    "salamander",
    "shaman",
    "gorgon",
    "druid",
    "elementalist",
    "bogWitch"
  ],
  "worm": {
    "formalName": "Worm",
    "availableFromStart": false,
    "requirements": {
      "spellsword": 4,
      "battlemage": 4
    },
    "baseHP": 110,
    "description": "Mud-dwellers. Sturdier than seems faire given their speed and damage. Poor vision and no foresight.",
    "unlockSite": "southeast",
    "skills": []
  },
  "5": {},
  "8": {}
}