{
  "spellsword": {
    "formalName": "Spellsword",
    "availableFromStart": true,
    "requirements": {
      "knight": 4,
      "wizard": 3
    },
    "baseHP": 100,
    "description": "Hot-blooded and decisive. A natural fighter with a broad affinity for the elements. This breed has a tendency to bite off more than they can chew.",
    "skills": []
  },
  "battlemage": {
    "formalName": "Battlemage",
    "availableFromStart": true,
    "requirements": {
      "knight": 3,
      "woods witch": 3
    },
    "baseHP": 120,
    "description": "Defensive and versatile melee mage with high health, healing spells, and terrain manipulation capabilities.",
    "skills": [
      [
        [{
          "name": "Surge",
          "skillLevel": 1,
          "range": "1-1",
          "areaOfEffect": "cone 1",
          "effects": {
            "damage": 35,
            "knockback": 1
          },
          "terrainEffects": {
            "water": 10,
            "breakDestructibles": true
          },
          "tags": ["damage", "knockback", "water", "breakDestructibles"]
        }], 
        [{
          "name": "Surge 2",
          "skillLevel": 2,
          "range": "1-1",
          "areaOfEffect": "cone 1",
          "effects": {
            "damage": 50,
            "knockback": 1
          },
          "terrainEffects": {
            "water": 15,
            "breakDestructibles": true
          },
          "tags": ["damage", "knockback", "water", "breakDestructibles"]
        }], 
        [{
          "name": "Surge 3",
          "skillLevel": 3,
          "range": "1-1",
          "areaOfEffect": "cone 2",
          "effects": {
            "damage": 40,
            "knockback": 1
          },
          "terrainEffects": {
            "water": 20,
            "breakDestructibles": true
          },
          "tags": ["damage", "knockback", "water", "breakDestructibles"]
        }]
      ],
      [
        [{
          "name": "Thirst",
          "skillLevel": 1,
          "range": "1-2",
          "areaOfEffect": "line",
          "effects": {
            "damage": 25,
            "healSelf": true
          },
          "terrainEffects": {
            "water": 3
          },
          "description": "Heals caster for damage done.",
          "tags": ["damage", "healSelf", "water"]
        }], 
        [{
          "name": "Thirst 2",
          "skillLevel": 2,
          "range": "1-1",
          "areaOfEffect": "cone 1",
          "effects": {
            "damage": 25,
            "healSelf": true
          },
          "terrainEffects": {
            "water": 6
          },
          "description": "Heals caster for damage done.",
          "tags": ["damage", "healSelf", "water"]
        }], 
        [{
          "name": "Thirst 3",
          "skillLevel": 3,
          "range": "1-1",
          "areaOfEffect": "C",
          "effects": {
            "damage": 25,
            "healSelf": true
          },
          "terrainEffects": {
            "water": 9
          },
          "description": "Heals caster for damage done.",
          "tags": ["damage", "healSelf", "water"]
        }]
      ],
      [
        [{
          "name": "Tend",
          "skillLevel": 1,
          "range": 1,
          "areaOfEffect": "single",
          "effects": {
            "heal": 40
          },
          "terrainEffects": {
            "growth": 9
          },
          "tags": ["heal", "growth"]
        }], 
        [{
          "name": "Tend 2",
          "skillLevel": 2,
          "range": 1,
          "areaOfEffect": "single",
          "effects": {
            "heal": 60
          },
          "terrainEffects": {
            "growth": 9,
            "createBrush": true
          },
          "tags": ["heal", "growth", "createBrush"]
        }], 
        [{
          "name": "Tend 3",
          "skillLevel": 3,
          "range": 1,
          "areaOfEffect": "single",
          "effects": {
            "heal": 80
          },
          "terrainEffects": {
            "growth": 9,
            "createBrush": true
          },
          "tags": ["heal", "growth", "createBrush"]
        }]
      ],
      [
        [{
          "name": "Soothe",
          "skillLevel": 1,
          "range": 1,
          "areaOfEffect": "square",
          "effects": {
            "heal": 25
          },
          "terrainEffects": {
            "smoothsEarth": true,
            "breakDestructibles": true
          },
          "tags": ["heal", "smoothsEarth", "breakDestructibles"]
        }], 
        [{
          "name": "Soothe 2",
          "skillLevel": 2,
          "range": 1,
          "areaOfEffect": "square",
          "effects": {
            "heal": 35
          },
          "terrainEffects": {
            "smoothsEarth": true,
            "breakDestructibles": true
          },
          "tags": ["heal", "smoothsEarth", "breakDestructibles"]
        }], 
        [{
          "name": "Soothe 3",
          "skillLevel": 3,
          "range": 1,
          "areaOfEffect": "square",
          "effects": {
            "heal": 45
          },
          "terrainEffects": {
            "smoothsEarth": true,
            "breakDestructibles": true
          },
          "tags": ["heal", "smoothsEarth", "breakDestructibles"]
        }]
      ],
      [
        [{
          "name": "Immovable",
          "skillLevel": 1,
          "passive": true
        }]
      ],
      [
        [{
          "name": "",
          "skillLevel": 1
        }], 
        [{
          "name": "",
          "skillLevel": 2
        }], 
        [{
          "name": "",
          "skillLevel": 3
        }]
      ],
      [
        [{
          "name": "",
          "skillLevel": 1
        }]
      ]
    ]
  },
  "woodsWitch": {
    "formalName": "Woods Witch",
    "availableFromStart": true,
    "requirements": {
      "goblin": 5
    },
    "baseHP": 70,
    "description": "Trustworthy, level-headed, with a truer understanding of life than most goblins. A ranged healer with  a variety of other capabilities.",
    "skills": []
  },
  "wizard": {
    "formalName": "Wizard",
    "availableFromStart": true,
    "requirements": {
      "archer": 4
    },
    "baseHP": 65,
    "description": "A well rounded mage witha mild affinity for the flame. Tends toward snark.",
    "skills": []
  },
  "1": {},
  "2": {},
  "salamander": {
    "formalName": "Salamander",
    "availableFromStart": false,
    "requirements": {
      "polearm": 3,
      "battlemage": 5
    },
    "baseHP": 95,
    "description": "Semi-aquatic. Thrives in marshes. Slimy and disease-ridden, but with a keen affinity for the healing arts.",
    "unlockSite": "west",
    "skills": []
  },
  "shaman": {
    "formalName": "Shaman",
    "availableFromStart": false,
    "requirements": {
      "battlemage": 6
    },
    "baseHP": 120,
    "description": "A disciplined healer who can control earth and plant. Can take a hit and deal one out, too.",
    "unlockSite": "north-of-west",
    "skills": []
  },
  "5": {},
  "6": {},
  "7": {},
  "8": {},
  "9": {},
  "0": {}
}